{"stat.walkOneCm":87427,"stat.useItem.minecraft.stone":53,"stat.leaveGame":19,"stat.jump":140,"stat.useItem.minecraft.sand":1,"stat.swimOneCm":839,"stat.fallOneCm":1175,"stat.useItem.minecraft.planks":21,"stat.crouchOneCm":41796,"stat.sprintOneCm":26777,"stat.useItem.minecraft.stained_glass":23,"achievement.exploreAllBiomes":{"value":0,"progress":["Beach","DesertHills","Desert M","Ocean","River","Forest","Plains","Desert"]},"achievement.openInventory":7,"stat.damageTaken":570,"stat.flyOneCm":154895,"stat.deaths":3,"stat.drop":1,"stat.mineBlock.minecraft.sand":2,"stat.playOneMinute":9460,"stat.damageDealt":245,"stat.useItem.minecraft.wool":102,"stat.timeSinceDeath":3559,"stat.diveOneCm":2690}